bmasterai/__init__.py
bmasterai/cli.py
bmasterai/integrations.py
bmasterai/logging.py
bmasterai/mcp_server.py
bmasterai/monitoring.py
bmasterai/reasoning_logger.py
bmasterai-0.2.2.dist-info/METADATA
bmasterai-0.2.2.dist-info/WHEEL
bmasterai-0.2.2.dist-info/entry_points.txt
bmasterai-0.2.2.dist-info/licenses/LICENSE
bmasterai-0.2.2.dist-info/RECORD
