Metadata-Version: 2.4
Name: bmasterai
Version: 0.2.2
Summary: A comprehensive Python framework for building multi-agent AI systems with advanced logging, monitoring, and integrations
Project-URL: Homepage, https://github.com/travis-burmaster/bmasterai
Project-URL: Issues, https://github.com/travis-burmaster/bmasterai/issues
Project-URL: Documentation, https://github.com/travis-burmaster/bmasterai#readme
Project-URL: Repository, https://github.com/travis-burmaster/bmasterai.git
Author-email: Travis Burmaster <travis@burmaster.com>
License-File: LICENSE
Keywords: agents,ai,automation,logging,monitoring,multi-agent
Classifier: Development Status :: 4 - Beta
Classifier: Intended Audience :: Developers
Classifier: License :: OSI Approved :: MIT License
Classifier: Operating System :: OS Independent
Classifier: Programming Language :: Python :: 3
Classifier: Programming Language :: Python :: 3.8
Classifier: Programming Language :: Python :: 3.9
Classifier: Programming Language :: Python :: 3.10
Classifier: Programming Language :: Python :: 3.11
Classifier: Programming Language :: Python :: 3.12
Classifier: Topic :: Scientific/Engineering :: Artificial Intelligence
Classifier: Topic :: Software Development :: Libraries :: Python Modules
Requires-Python: >=3.8
Requires-Dist: openai>=1.0.0
Requires-Dist: psutil>=5.9.0
Requires-Dist: pyyaml>=6.0
Requires-Dist: requests>=2.28.0
Provides-Extra: all
Requires-Dist: black>=22.0.0; extra == 'all'
Requires-Dist: celery>=5.2.0; extra == 'all'
Requires-Dist: discord-py>=2.0.0; extra == 'all'
Requires-Dist: flake8>=5.0.0; extra == 'all'
Requires-Dist: mypy>=1.0.0; extra == 'all'
Requires-Dist: pymongo>=4.0.0; extra == 'all'
Requires-Dist: pytest-cov>=4.0.0; extra == 'all'
Requires-Dist: pytest>=7.0.0; extra == 'all'
Requires-Dist: redis>=4.0.0; extra == 'all'
Requires-Dist: slack-sdk>=3.19.0; extra == 'all'
Provides-Extra: dev
Requires-Dist: black>=22.0.0; extra == 'dev'
Requires-Dist: flake8>=5.0.0; extra == 'dev'
Requires-Dist: mypy>=1.0.0; extra == 'dev'
Requires-Dist: pytest-cov>=4.0.0; extra == 'dev'
Requires-Dist: pytest>=7.0.0; extra == 'dev'
Provides-Extra: integrations
Requires-Dist: celery>=5.2.0; extra == 'integrations'
Requires-Dist: discord-py>=2.0.0; extra == 'integrations'
Requires-Dist: pymongo>=4.0.0; extra == 'integrations'
Requires-Dist: redis>=4.0.0; extra == 'integrations'
Requires-Dist: slack-sdk>=3.19.0; extra == 'integrations'
